{"items": [{"shortCode": "7663233342715923733", "url": "https://www.tiktok.com/@gocleanco/video/7663233342715923733", "caption": "I don\u2019t use coffee machines at hotels but now I won\u2019t use them at peoples houses \ud83e\udee0 #cleantok #coffee #fyp #cleaning ", "timestamp": "2026-07-16T20:59:21.000Z", "videoDuration": 11, "videoPlayCount": 8361, "likesCount": 75, "commentsCount": 6, "displayUrl": "https://p16-common-sign.tiktokcdn-us.com/tos-alisg-p-0037/oM5WI2CqBgAQ6CRSAEeEfAzAynSDWFtYUUuj4E~tplv-tiktokx-origin.image?dr=9636&x-expires=1784595600&x-signature=ew1QJvRRcjRUdfaaFelddDOSiHg%3D&t=4d5b0474&ps=13740610&shp=81f88b70&shcp=43f4a2f9&idc=useast8", "ownerUsername": "gocleanco", "ownerFullName": "gocleanco", "platform": "tiktok", "history": [{"date": "2026-07-18", "plays": 8158, "likes": 70, "comments": 6}, {"date": "2026-07-19", "plays": 8361, "likes": 75, "comments": 6}], "still_climbing": false}, {"shortCode": "7663231493325557013", "url": "https://www.tiktok.com/@gocleanco/video/7663231493325557013", "caption": "How to clean your bins and keep bugs and animals out of them. \ud83d\udc1b\ud83d\udc3b\nOne step I forgot to show here was I poured some Pine-Sol in the bottom of the bins to soften the gunk and filled with a bit of water and let them soak for an hour in the sun! @Pine-Sol \n#fyp #CleanTok #outdoorcleaning #garbage ", "timestamp": "2026-07-16T20:52:07.000Z", "videoDuration": 96, "videoPlayCount": 127800, "likesCount": 754, "commentsCount": 10, "displayUrl": "https://p16-common-sign.tiktokcdn-us.com/tos-alisg-p-0037/oU6pilRBiAACNAZAYEAB8raBlBIbvPzIdEHEl~tplv-tiktokx-origin.image?dr=9636&x-expires=1784595600&x-signature=%2FfJPt4mOF38%2BpbKY9EzB8IaoHog%3D&t=4d5b0474&ps=13740610&shp=81f88b70&shcp=43f4a2f9&idc=useast8", "ownerUsername": "gocleanco", "ownerFullName": "gocleanco", "platform": "tiktok", "history": [{"date": "2026-07-18", "plays": 104300, "likes": 630, "comments": 10}, {"date": "2026-07-19", "plays": 127800, "likes": 754, "comments": 10}], "still_climbing": false, "is_relevant": true, "videoUrl": "https://api.apify.com/v2/key-value-stores/2d8T968WDzKoVyNJA/records/video-gocleanco-20260716205207-7663231493325557013.mp4"}, {"shortCode": "7658334839564700948", "url": "https://www.tiktok.com/@gocleanco/video/7658334839564700948", "caption": "Come find my custom DIRTY SODA on the secret influencer menu at @covet sips + sweets at the Calgary Stampede from July 3rd-12th.\n\nDirty Bastard by @gocleanco\n\n\u2022 Coke zero, extra ice\n\u2022 A splash of fresh raspberry pur\u00e9e \n\u2022 A splash of peach pur\u00e9e \n\u2022 Two fresh lime wedges \n\u2022 Finished with a drizzle of coconut cream\n\nit\u2019s sweet, tart, cream, fizzy - tastes just like summer. \n\nIf your headed to stampede, order my dirty soda, you dirty bastards. \ud83e\udd20\ud83e\udd64\n#calgarystampede #dirtysoda #stampede2026 ", "timestamp": "2026-07-03T16:10:37.000Z", "videoDuration": 26, "videoPlayCount": 4738, "likesCount": 76, "commentsCount": 1, "displayUrl": "https://p19-common-sign.tiktokcdn-us.com/tos-alisg-p-0037/o4LbTmB0IiA7IdBRzDiUV3ESB8eJfRRHq2wtg4~tplv-tiktokx-origin.image?dr=9636&x-expires=1784595600&x-signature=nVWAZ8qPFEk1KfoDPcHn7WjZalM%3D&t=4d5b0474&ps=13740610&shp=81f88b70&shcp=43f4a2f9&idc=useast8", "ownerUsername": "gocleanco", "ownerFullName": "gocleanco", "platform": "tiktok", "history": [{"date": "2026-07-18", "plays": 4720, "likes": 76, "comments": 1}, {"date": "2026-07-19", "plays": 4738, "likes": 76, "comments": 1}], "still_climbing": false, "is_relevant": false, "videoUrl": "https://api.apify.com/v2/key-value-stores/2d8T968WDzKoVyNJA/records/video-gocleanco-20260703161037-7658334839564700948.mp4"}]}